Metadata-Version: 2.1
Name: perfect_square
Version: 1.0.0
Summary: Simple printer of perfect squares up to a given number
Author: Sharon Kwikiriza
